{
  "/": {
    "pt-BR": {
      "head": {
        "title": "Morkato - Bot | Apenas um simples bot",
        "description": "Apenas um simples bot.",
        
        "og:site_name": "Morkato Bot",
        "og:type": "website",
        "og:title": "$title",
        "og:description": "$description"
      },
      "body": {
        "login": "Fazer Login"
      }
    },
    "en": {
      "head": {
        "title": "Morkato - Bot | Just a simple bot",
        "description": "Just a simple bot.",
        
        "og:site_name": "Morkato Bot",
        "og:type": "website",
        "og:title": "$title",
        "og:description": "$description"
      },
      "body": {
        "login": "Login"
      }
    }
  },
  "/dashboad": {
    "pt-BR": {

    },
    "en": {

    }
  }
}